odoo/addons/purchase_open_qty/README.rst
odoo/addons/purchase_open_qty/__init__.py
odoo/addons/purchase_open_qty/__manifest__.py
odoo/addons/purchase_open_qty/init_hook.py
odoo/addons/purchase_open_qty/i18n/de.po
odoo/addons/purchase_open_qty/i18n/es.po
odoo/addons/purchase_open_qty/i18n/es_MX.po
odoo/addons/purchase_open_qty/i18n/es_PE.po
odoo/addons/purchase_open_qty/i18n/fi.po
odoo/addons/purchase_open_qty/i18n/fr.po
odoo/addons/purchase_open_qty/i18n/fr_BE.po
odoo/addons/purchase_open_qty/i18n/gl.po
odoo/addons/purchase_open_qty/i18n/hr.po
odoo/addons/purchase_open_qty/i18n/it.po
odoo/addons/purchase_open_qty/i18n/nl.po
odoo/addons/purchase_open_qty/i18n/nl_NL.po
odoo/addons/purchase_open_qty/i18n/pt_BR.po
odoo/addons/purchase_open_qty/i18n/pt_PT.po
odoo/addons/purchase_open_qty/i18n/purchase_open_qty.pot
odoo/addons/purchase_open_qty/i18n/ro.po
odoo/addons/purchase_open_qty/i18n/sl.po
odoo/addons/purchase_open_qty/i18n/vi_VN.po
odoo/addons/purchase_open_qty/i18n/zh_CN.po
odoo/addons/purchase_open_qty/models/__init__.py
odoo/addons/purchase_open_qty/models/purchase_order.py
odoo/addons/purchase_open_qty/readme/CONTRIBUTORS.rst
odoo/addons/purchase_open_qty/readme/DESCRIPTION.rst
odoo/addons/purchase_open_qty/readme/USAGE.rst
odoo/addons/purchase_open_qty/static/description/icon.png
odoo/addons/purchase_open_qty/static/description/index.html
odoo/addons/purchase_open_qty/tests/__init__.py
odoo/addons/purchase_open_qty/tests/test_purchase_open_qty.py
odoo/addons/purchase_open_qty/views/purchase_view.xml
odoo14_addon_purchase_open_qty-14.0.1.1.2.dist-info/METADATA
odoo14_addon_purchase_open_qty-14.0.1.1.2.dist-info/WHEEL
odoo14_addon_purchase_open_qty-14.0.1.1.2.dist-info/top_level.txt
odoo14_addon_purchase_open_qty-14.0.1.1.2.dist-info/RECORD
